crxftp/FtpManager.py
crxftp/FtpSupporting.py
crxftp/__init__.py
crx_ftp-1.0.1.dist-info/METADATA
crx_ftp-1.0.1.dist-info/WHEEL
crx_ftp-1.0.1.dist-info/top_level.txt
crx_ftp-1.0.1.dist-info/RECORD
